SBGv001_granules/L1CTRAD.py
SBGv001_granules/L2TLSTE.py
SBGv001_granules/L2TSTARS.py
SBGv001_granules/L4TESI.py
SBGv001_granules/L4TJET.py
SBGv001_granules/L4TWUE.py
SBGv001_granules/SBGv001_granules.py
SBGv001_granules/__init__.py
SBGv001_granules/colors.py
SBGv001_granules/granule.py
SBGv001_granules/open_granule.py
SBGv001_granules/tiled_granule.py
SBGv001_granules/version.txt
SBGv001_granules/write_XML_metadata.py
SBGv001_granules/timer/__init__.py
SBGv001_granules/timer/timer.py
sbgv001_granules-1.0.1.dist-info/licenses/LICENSE
sbgv001_granules-1.0.1.dist-info/METADATA
sbgv001_granules-1.0.1.dist-info/WHEEL
sbgv001_granules-1.0.1.dist-info/top_level.txt
sbgv001_granules-1.0.1.dist-info/RECORD
