Metadata-Version: 2.4
Name: SBGv001-granules
Version: 1.0.1
Summary: SBG-TIR OTTER Collection 1 Data Product Granule Encapsulation Classes
Author-email: "Gregory H. Halverson" <gregory.h.halverson@jpl.nasa.gov>
Project-URL: Homepage, https://github.com/sbg-tir/SBGv001-granules
Classifier: Programming Language :: Python :: 3
Classifier: Operating System :: OS Independent
Requires-Python: >=3.10
License-File: LICENSE
Requires-Dist: colored-logging
Requires-Dist: matplotlib
Requires-Dist: numpy
Requires-Dist: rasters
Requires-Dist: python-dateutil
Requires-Dist: shapely
Provides-Extra: dev
Requires-Dist: build; extra == "dev"
Requires-Dist: pytest>=6.0; extra == "dev"
Requires-Dist: pytest-cov; extra == "dev"
Requires-Dist: jupyter; extra == "dev"
Requires-Dist: pytest; extra == "dev"
Requires-Dist: twine; extra == "dev"
Dynamic: license-file
